{
  "blocks": [
    {
      "name": "Nothing",
      "hp": -1,
      "solid": false,
      "transparent": true,
      "texture": 0,
      "dropped_item": 0,
      "count": 0,
      "block_type": 4,
      "output_id": 0,
      "regen": false,
      "regen_ticks": 0,
      "hardness": -1,
      "ignition": -1,
      "extinguish_id": 0,
      "id": 0
    },

    {
      "name": "Stone",
      "hp": 4,
      "solid": true,
      "transparent": false,
      "texture": 1,
      "dropped_item": 17,
      "count": 4,
      "block_type": 0,
      "output_id": 0,
      "regen": false,
      "regen_ticks": 0,
      "hardness": 2,
      "ignition": 1612,
      "extinguish_id": 23,
      "id": 1
    },
      
    {
      "name": "Grass",
      "hp": 2,
      "solid": true,
      "transparent": false,
      "texture": 2,
      "dropped_item": 5,
      "count": 2,
      "block_type": 2,
      "output_id": 5,
      "regen": false,
      "regen_ticks": 0,
      "hardness": 0,
      "ignition": 600,
      "extinguish_id": 0,
      "id": 2
    },
      
    {
      "name": "Trunk",
      "hp": 2,
      "solid": true,
      "transparent": true,
      "texture":  3,
      "dropped_item": 16,
      "count": 2,
      "block_type": 1,
      "output_id": 0,
      "regen": false,
      "regen_ticks": 0,
      "hardness": 2,
      "ignition": 644,
      "extinguish_id": 12,
      "id": 3
    },
      
    {
      "name": "Leaves",
      "hp": 2,
      "solid": true,
      "transparent": true,
      "texture": 4,
      "dropped_item": 16,
      "count": 2,
      "block_type": 1,
      "output_id": 0,
      "regen": false,
      "regen_ticks": 0,
      "hardness": 1,
      "ignition": 500,
      "extinguish_id": 12,
      "id": 4
    },
      
    {
      "name": "Dirt",
      "hp": 2,
      "solid": true,
      "transparent": false,
      "texture": 5,
      "dropped_item": 5,
      "count": 1,
      "block_type": 2,
      "output_id": 0,
      "regen": false,
      "regen_ticks": 0,
      "hardness": 0,
      "ignition": -1,
      "extinguish_id": 5,
      "id": 5
    },
      
    {
      "name": "Water",
      "hp": -1,
      "solid": false,
      "transparent": true,
      "texture": 6,
      "dropped_item": 6,
      "count": 0,
      "block_type": 2,
      "output_id": 0,
      "regen": false,
      "regen_ticks": 0,
      "hardness": 0,
      "ignition": 373,
      "extinguish_id": 24,
      "id": 6
    },
      
    {
      "name": "Sand",
      "hp": 2,
      "solid": true,
      "transparent": false,
      "texture": 7,
      "dropped_item": 7,
      "count": 1,
      "block_type": 2,
      "output_id": 0,
      "regen": false,
      "regen_ticks": 0,
      "hardness": 0,
      "ignition": 1972,
      "extinguish_id": 23,
      "id": 7
    },
      
    {
      "name": "Nokium",
      "hp": -1,
      "solid": true,
      "transparent": false,
      "texture": 8,
      "dropped_item": 8,
      "count": 1,
      "block_type": 4,
      "output_id": 8,
      "regen": false,
      "regen_ticks": 0,
      "hardness": -1,
      "ignition": -1,
      "extinguish_id": 8,
      "id": 8
    },
      
    {
      "name": "Clay",
      "hp": 2,
      "solid": true,
      "transparent": false,
      "texture": 9,
      "dropped_item": 9,
      "count": 1,
      "block_type": 2,
      "output_id": 0,
      "regen": false,
      "regen_ticks": 0,
      "hardness": 1,
      "ignition": 1523,
      "extinguish_id": 23,
      "id": 9
    },
      
    {
      "name": "Thatch",
      "hp": 1,
      "solid": true,
      "transparent": false,
      "texture": 10,
      "dropped_item": 10,
      "count": 1,
      "block_type": 5,
      "output_id": 0,
      "regen": false,
      "regen_ticks": 0,
      "hardness": 0,
      "ignition": 400,
      "extinguish_id": 12,
      "id": 10
    },
      
    {
      "name": "Fire",
      "hp": -1,
      "solid": false,
      "transparent": true,
      "texture": 11,
      "dropped_item": 11,
      "count": 1,
      "block_type": 4,
      "output_id": 11,
      "regen": true,
      "regen_ticks": 10000,
      "hardness": -1,
      "ignition": 1400,
      "extinguish_id": 12,
      "id": 11
    },
      
    {
      "name": "Charcoal",
      "hp": 1,
      "solid": false,
      "transparent": true,
      "texture": 12,
      "dropped_item": 12,
      "count": 1,
      "block_type": 1,
      "output_id": 0,
      "regen": false,
      "regen_ticks": 0,
      "hardness": 0,
      "ignition": 413,
      "extinguish_id": 0,
      "id": 12
    },
      
    {
      "name": "Rock wall",
      "hp": 4,
      "solid": true,
      "transparent": false,
      "texture": 16,
      "dropped_item": 14,
      "count": 2,
      "block_type": 0,
      "output_id": 0,
      "regen": false,
      "regen_ticks": 0,
      "hardness": 3,
      "ignition": 1612,
      "extinguish_id": 12,
      "id": 13
    },
      
    {
      "name": "Rocks",
      "hp": 2,
      "solid": false,
      "transparent": true,
      "texture": 17,
      "dropped_item": 14,
      "count": 1,
      "block_type": 0,
      "output_id": 0,
      "regen": false,
      "regen_ticks": 0,
      "hardness": 0,
      "ignition": 1612,
      "extinguish_id": 23,
      "id": 14
    },
    {
      "name": "Stick",
      "hp": 1,
      "solid": false,
      "transparent": true,
      "texture": 19,
      "dropped_item": 15,
      "count": 1,
      "block_type": 5,
      "output_id": 0,
      "regen": false,
      "regen_ticks": 0,
      "hardness": 0,
      "ignition": 400,
      "extinguish_id": 12,
      "id": 15
    },
      
    {
      "name": "Branch",
      "hp": 1,
      "solid": false,
      "transparent": true,
      "texture": 20,
      "dropped_item": 16,
      "count": 1,
      "block_type": 5,
      "output_id": 0,
      "regen": false,
      "regen_ticks": 0,
      "hardness": 0,
      "ignition": 400,
      "extinguish_id": 12,
      "id": 16
    },
      
    {
      "name": "Berry bush",
      "hp": 2,
      "solid": true,
      "transparent": true,
      "texture": 21,
      "dropped_item": 19,
      "count": 1,
      "block_type": 5,
      "output_id": 18,
      "regen": false,
      "regen_ticks": 0,
      "hardness": 0,
      "ignition": 400,
      "extinguish_id": 12,
      "id": 17
    },
      
    {
      "name": "Bush",
      "hp": 2,
      "solid": true,
      "transparent": true,
      "texture": 22,
      "dropped_item": 16,
      "count": 1,
      "block_type": 5,
      "output_id": 0,
      "regen": true,
      "regen_ticks": 100000,
      "hardness": 0,
      "ignition": 400,
      "extinguish_id": 12,
      "id": 18
    },
      
    {
      "name": "Red berries",
      "hp": 1,
      "solid": false,
      "transparent": true,
      "texture": 23,
      "dropped_item": 19,
      "count": 1,
      "block_type": 6,
      "output_id": 0,
      "regen": false,
      "regen_ticks": 0,
      "hardness": 0,
      "ignition": 300,
      "extinguish_id": 12,
      "id": 19
    },
      
    {
      "name": "Sharpened rock",
      "hp": 1,
      "solid": false,
      "transparent": true,
      "texture": 33,
      "dropped_item": 20,
      "count": 1,
      "block_type": 7,
      "output_id": 0,
      "regen": false,
      "regen_ticks": 0,
      "hardness": 1,
      "ignition": 1612,
      "extinguish_id": 23,
      "id": 20
    },
      
    {
      "name": "Sharpened stick",
      "hp": 1,
      "solid": false,
      "transparent": true,
      "texture": 35,
      "dropped_item": 21,
      "count": 1,
      "block_type": 7,
      "output_id": 0,
      "regen": false,
      "regen_ticks": 0,
      "hardness": 0,
      "ignition": 400,
      "extinguish_id": 12,
      "id": 21
    },
      
    {
      "name": "Stone axe",
      "hp": 1,
      "solid": false,
      "transparent": true,
      "texture": 36,
      "dropped_item": 22,
      "count": 1,
      "block_type": 7,
      "output_id": 0,
      "regen": false,
      "regen_ticks": 0,
      "hardness": 2,
      "ignition": 400,
      "extinguish_id": 12,
      "id": 22
    },

    {
      "name": "Molten rock",
      "hp": -1,
      "solid": false,
      "transparent": true,
      "texture": 23,
      "dropped_item": 14,
      "count": 1,
      "block_type": 0,
      "output_id": 0,
      "regen": true,
      "regen_ticks": 10000,
      "hardness": -1,
      "extinguish_id": 14,
      "id": 23
    },

    {
      "name": "Steam",
      "hp": -1,
      "solid": false,
      "transparent": true,
      "texture": 24,
      "dropped_item": 24,
      "count": 0,
      "block_type": 4,
      "output_id": 6,
      "regen": 1,
      "regen_ticks": 10000,
      "hardness": -1,
      "extinguish_id": 6,
      "id": 24
    }
  ]
}
